{
    "data": [
        {
            "banner": "Black Frideals",
            "name": "Samsung Galaxy S21 FE 5G",
            "image": "https://images.ctfassets.net/t00ajdlq0g9p/6INHVXkShMMZ6Sozg1UfcE/1a6545abee221a6212a251938cbfff78/samsung-galsxy-s21-5G-graphite-front.png?h=201&w=268&fm=webp&q=100",
            "vendor": "Samsung",
            "properties": {
                "cost": {
                    "priceSign": "$",
                    "standard": 0,
                    "zero": ".00",
                    "down": "/down",
                    "reduced": "$48.88/mo.±Monthly financing after credit$9.58/mo.±(After bill credit)with Fido Payment"
                }
            },
            "taxes": ["Taxes extra", "24 mos", "0% APR"],
            "fullPrice": 1173,
            "content": "Includes $39.30/mo. credit (appears on bill under ‘Monthly charges’)"
        },
        {
            "banner": "Cyber deal",
            "name": "Samsung Galaxy A53 5G",
            "image": "https://images.ctfassets.net/t00ajdlq0g9p/7gINZkPs3PAxh7oZg6ki0f/5a84bd4e50f35a3da26f2100ad000977/galaxy-a53-5G-front__1_.png?h=201&w=268&fm=webp&q=100",
            "vendor": "Samsung",
            "properties": {
                "cost": {
                    "priceSign": "$",
                    "standard": 0,
                    "zero": ".00",
                    "down": "/down",
                    "reduced": "$48.88/mo.±Monthly financing after credit$9.58/mo.±(After bill credit)with Fido Payment"
                }
            },
            "taxes": ["Taxes extra", "24 mos", "0% APR"],
            "fullPrice": 1173,
            "content": "Includes $39.30/mo. credit (appears on bill under ‘Monthly charges’)"
        },

        {
            "banner": "cyber deal",
            "name": "iPhone 12",
            "image": "https://images.ctfassets.net/t00ajdlq0g9p/7FD60LS70ADulmHYrvcAlN/0f3c2388a0f38f59b694ca971919b0cc/iPhone-12-black-01.png?h=201&w=268&fm=webp&q=100",
            "vendor": "Apple",
            "properties": {
                "cost": {
                    "priceSign": "$",
                    "standard": 0,
                    "zero": ".00",
                    "down": "/down",
                    "reduced": "$48.88/mo.±Monthly financing after credit$9.58/mo.±(After bill credit)with Fido Payment"
                }
            },
            "taxes": ["Taxes extra", "24 mos", "0% APR"],
            "fullPrice": 1173.0,
            "content": "Includes $39.30/mo. credit (appears on bill under ‘Monthly charges’)"
        },

        {
            "banner": "Black Frideals",
            "name": "Samsung Galaxy S21 FE 5G",
            "image": "https://images.ctfassets.net/t00ajdlq0g9p/6INHVXkShMMZ6Sozg1UfcE/1a6545abee221a6212a251938cbfff78/samsung-galsxy-s21-5G-graphite-front.png?h=201&w=268&fm=webp&q=100",
            "vendor": "Samsung",
            "properties": {
                "cost": {
                    "priceSign": "$",
                    "standard": 0,
                    "zero": ".00",
                    "down": "/down",
                    "reduced": "$48.88/mo.±Monthly financing after credit$9.58/mo.±(After bill credit)with Fido Payment"
                }
            },
            "taxes": ["Taxes extra", "24 mos", "0% APR"],
            "fullPrice": 1173.0,
            "content": "Includes $39.30/mo. credit (appears on bill under ‘Monthly charges’)"
        },
        
       {
            "banner": "Black Frideals",
            "name": "Samsung Galaxy S21 FE 5G",
            "image": "https://images.ctfassets.net/t00ajdlq0g9p/6INHVXkShMMZ6Sozg1UfcE/1a6545abee221a6212a251938cbfff78/samsung-galsxy-s21-5G-graphite-front.png?h=201&w=268&fm=webp&q=100",
            "vendor": "Samsung",
            "properties": {
                "cost": {
                    "priceSign":"$",
                    "standard": 0,
                    "zero":".00",
                    "down":"/down",
                    "reduced": "$48.88/mo.±Monthly financing after credit$9.58/mo.±(After bill credit)with Fido Payment"
                }
            },
            "taxes": ["Taxes extra", "24 mos", "0% APR"],
            "fullPrice": 1173.0,
            "content": "Includes $39.30/mo. credit (appears on bill under ‘Monthly charges’)"
        }
        
    ]
}
